nbta/__init__.py
nbta/convert.py
nbta/formative.py
nbta/grading.py
nbta/notebooks.py
nbta/summative.py
nbta/utils.py
nbta-0.2.7.1.data/scripts/nbta-run
tests/__init__.py
nbta-0.2.7.1.dist-info/LICENSE.txt
nbta-0.2.7.1.dist-info/METADATA
nbta-0.2.7.1.dist-info/WHEEL
nbta-0.2.7.1.dist-info/top_level.txt
nbta-0.2.7.1.dist-info/RECORD
